pai/__init__.py
pai/decorator.py
pai/api/__init__.py
pai/api/base.py
pai/api/client_factory.py
pai/api/paiflow.py
pai/api/sts.py
pai/api/workspace.py
pai/common/__init__.py
pai/common/utils.py
pai/core/__init__.py
pai/core/estimator.py
pai/core/exception.py
pai/core/job.py
pai/core/model.py
pai/core/session.py
pai/core/transformer.py
pai/core/workspace.py
pai/libs/__init__.py
pai/libs/aliyunsdkaiworkspace/__init__.py
pai/libs/aliyunsdkaiworkspace/request/__init__.py
pai/libs/aliyunsdkaiworkspace/request/v20200814/CreateMemberRequest.py
pai/libs/aliyunsdkaiworkspace/request/v20200814/CreateTenantRequest.py
pai/libs/aliyunsdkaiworkspace/request/v20200814/GetAdminPermissionRequest.py
pai/libs/aliyunsdkaiworkspace/request/v20200814/GetDefaultWorkspaceRequest.py
pai/libs/aliyunsdkaiworkspace/request/v20200814/GetPermissionRequest.py
pai/libs/aliyunsdkaiworkspace/request/v20200814/GetWorkspaceRequest.py
pai/libs/aliyunsdkaiworkspace/request/v20200814/ListAdminWorkspacesRequest.py
pai/libs/aliyunsdkaiworkspace/request/v20200814/ListMembersRequest.py
pai/libs/aliyunsdkaiworkspace/request/v20200814/ListPermissionsRequest.py
pai/libs/aliyunsdkaiworkspace/request/v20200814/ListSubUsersRequest.py
pai/libs/aliyunsdkaiworkspace/request/v20200814/ListWorkspacesRequest.py
pai/libs/aliyunsdkaiworkspace/request/v20200814/UpdateMemberRequest.py
pai/libs/aliyunsdkaiworkspace/request/v20200814/UpdateWorkspaceRequest.py
pai/libs/aliyunsdkaiworkspace/request/v20200814/__init__.py
pai/libs/aliyunsdkpaiflow/__init__.py
pai/libs/aliyunsdkpaiflow/request/__init__.py
pai/libs/aliyunsdkpaiflow/request/v20200328/CreatePipelineRequest.py
pai/libs/aliyunsdkpaiflow/request/v20200328/CreateRunRequest.py
pai/libs/aliyunsdkpaiflow/request/v20200328/DeletePipelineRequest.py
pai/libs/aliyunsdkpaiflow/request/v20200328/DescribePipelineRequest.py
pai/libs/aliyunsdkpaiflow/request/v20200328/GetMyProviderRequest.py
pai/libs/aliyunsdkpaiflow/request/v20200328/GetNodeDetailRequest.py
alibaba_pai-0.1.7.dist-info/LICENSE.txt
alibaba_pai-0.1.7.dist-info/METADATA
alibaba_pai-0.1.7.dist-info/WHEEL
alibaba_pai-0.1.7.dist-info/top_level.txt
alibaba_pai-0.1.7.dist-info/RECORD
