Metadata-Version: 2.1
Name: alibaba-pai
Version: 0.1.7
Summary: Alibaba Cloud PAI Python SDK
Home-page: https://www.aliyun.com/product/bigdata/product/learn
Author: Alibaba PAI team
License: Apache License 2.0
Keywords: ML Alibaba Cloud PAI Training Inference Pipeline
Platform: UNKNOWN
Requires-Python: >=2.7
Requires-Dist: aliyun-python-sdk-core (==2.13.25)
Requires-Dist: aliyun-python-sdk-sts (>=3.0.2)
Requires-Dist: enum34 (>=1.1.10)
Requires-Dist: graphviz (>=0.14)
Requires-Dist: numpy (>=1.16.0)
Requires-Dist: oss2 (>=2.8.0)
Requires-Dist: pyodps (>=0.9.3.2)
Requires-Dist: pyyaml (>=5.3.1)
Requires-Dist: six (>=1.15.0)
Requires-Dist: importlib-metadata (==2.0.0)
